icmplib/__init__.py
icmplib/exceptions.py
icmplib/ip.py
icmplib/models.py
icmplib/ping.py
icmplib/sockets.py
icmplib/traceroute.py
icmplib/utils.py
icmplibv2-1.0.6.dist-info/LICENSE
icmplibv2-1.0.6.dist-info/METADATA
icmplibv2-1.0.6.dist-info/WHEEL
icmplibv2-1.0.6.dist-info/top_level.txt
icmplibv2-1.0.6.dist-info/RECORD
