Metadata-Version: 2.1
Name: icmplibv2
Version: 1.0.6
Summary: Easily forge ICMP packets and make your own ping and traceroute.
Home-page: https://github.com/ValentinBELYN/icmplib
Author: Valentin BELYN
Author-email: valentin-hello@gmx.com
License: GNU Lesser General Public License v3.0
Keywords: pure,implementation,icmp,sockets,ping,multiping,traceroute,ipv4,ipv6,python3
Platform: UNKNOWN
Classifier: Development Status :: 5 - Production/Stable
Classifier: Intended Audience :: Developers
Classifier: License :: OSI Approved :: GNU Lesser General Public License v3 or later (LGPLv3+)
Classifier: Operating System :: OS Independent
Classifier: Programming Language :: Python :: 3
Classifier: Programming Language :: Python :: 3 :: Only
Classifier: Programming Language :: Python :: 3.6
Classifier: Programming Language :: Python :: 3.7
Classifier: Programming Language :: Python :: 3.8
Classifier: Topic :: Software Development :: Libraries
Classifier: Topic :: Software Development :: Libraries :: Python Modules
Requires-Python: >=3.6
